stacia/__init__.py
stacia-0.0.1a0.dist-info/METADATA
stacia-0.0.1a0.dist-info/WHEEL
stacia-0.0.1a0.dist-info/top_level.txt
stacia-0.0.1a0.dist-info/RECORD
